{
  "version": "2.1.0",
  "benefitFieldPrefix": "benefit_",
  "benefitKeys": [
    "unlimited_contacts",
    "post_comment_dm_reply",
    "post_comment_reply_automation",
    "reel_comment_dm_reply",
    "reel_comment_reply_automation",
    "share_reel_to_admin",
    "share_post_to_admin",
    "super_profile",
    "inbox_menu",
    "collect_email",
    "suggest_more",
    "followers_only",
    "once_per_user_24h",
    "comment_moderation",
    "seen_typing",
    "welcome_message",
    "convo_starters",
    "dm_automation",
    "story_automation",
    "no_watermark",
    "global_trigger",
    "mentions",
    "instagram_live_automation",
    "priority_support"
  ],
  "benefitStorageKeys": {
    "post_comment_reply_automation": "post_comment_reply",
    "reel_comment_reply_automation": "reel_comment_reply"
  },
  "legacyBenefitStorageKeys": {
    "post_comment_dm_reply": ["post_comment_dm_automation"],
    "reel_comment_dm_reply": ["reel_comment_dm_automation"],
    "share_reel_to_admin": ["share_reel_to_dm"],
    "share_post_to_admin": ["share_post_to_dm"],
    "post_comment_reply_automation": ["post_comment_reply"],
    "reel_comment_reply_automation": ["reel_comment_reply"]
  },
  "benefitAliases": {
    "post_comment_dm": "post_comment_dm_reply",
    "post_comment_dm_automation": "post_comment_dm_reply",
    "post_comment_reply": "post_comment_reply_automation",
    "reel_comment_dm": "reel_comment_dm_reply",
    "reel_comment_dm_automation": "reel_comment_dm_reply",
    "reel_comment_reply": "reel_comment_reply_automation",
    "share_reel_to_dm": "share_reel_to_admin",
    "share_post_to_dm": "share_post_to_admin",
    "dm_automations": "dm_automation",
    "auto_reply_dm_keywords": "dm_automation",
    "story_mentions_custom_dm": "mentions",
    "mention": "mentions",
    "email_collector": "collect_email",
    "webhook_integrations": "collect_email",
    "seen_typing_indicator": "seen_typing",
    "no_watermark_branding": "no_watermark",
    "once_per_user": "once_per_user_24h",
    "instagram_connections": "instagram_connections_limit"
  },
  "limitKeys": [
    "instagram_connections_limit",
    "instagram_link_limit",
    "actions_per_hour_limit",
    "actions_per_day_limit",
    "actions_per_month_limit",
    "hourly_action_limit",
    "daily_action_limit",
    "monthly_action_limit"
  ],
  "toggleFeatureMap": {
    "suggest_more_enabled": "suggest_more",
    "collect_email_enabled": "collect_email",
    "seen_typing_enabled": "seen_typing",
    "followers_only": "followers_only",
    "once_per_user_24h": "once_per_user_24h"
  },
  "automationTypeFeatureMap": {
    "dm": "dm_automation",
    "global": "global_trigger",
    "comment": "post_comment_dm_reply",
    "post": "post_comment_dm_reply",
    "reel": "reel_comment_dm_reply",
    "story": "story_automation",
    "live": "instagram_live_automation",
    "mention": "mentions",
    "mentions": "mentions",
    "welcome_message": "welcome_message",
    "inbox_menu": "inbox_menu",
    "convo_starter": "convo_starters",
    "suggest_more": "suggest_more",
    "comment_moderation": "comment_moderation",
    "moderation_hide": "comment_moderation",
    "moderation_delete": "comment_moderation"
  },
  "commentReplyFeatureMap": {
    "comment": "post_comment_reply_automation",
    "post": "post_comment_reply_automation",
    "reel": "reel_comment_reply_automation"
  },
  "shareTriggerFeatureMap": {
    "comment": "share_post_to_admin",
    "post": "share_post_to_admin",
    "reel": "share_reel_to_admin"
  },
  "featureLabels": {
    "unlimited_contacts": "Unlimited Contacts",
    "post_comment_dm_reply": "Post Comment DM Reply",
    "post_comment_reply_automation": "Post Comment Reply Automation",
    "reel_comment_dm_reply": "Reel Comment DM Reply",
    "reel_comment_reply_automation": "Reel Comment Reply Automation",
    "share_reel_to_admin": "Share Reel To Admin",
    "share_post_to_admin": "Share Post To Admin",
    "super_profile": "Super Profile",
    "inbox_menu": "Inbox Menu",
    "collect_email": "Collect Email",
    "suggest_more": "Suggest More",
    "followers_only": "Followers-only",
    "comment_moderation": "Comment Moderation",
    "seen_typing": "Seen Typing",
    "welcome_message": "Welcome Message",
    "convo_starters": "Convo Starters",
    "dm_automation": "DM Automation",
    "story_automation": "Story Automation",
    "no_watermark": "No Watermark",
    "global_trigger": "Global Trigger",
    "mentions": "Mentions",
    "instagram_live_automation": "Instagram Live Automation",
    "priority_support": "Priority Support",
    "once_per_user_24h": "Once Per User / 24h"
  },
  "planCatalog": {
    "free": {
      "name": "Free Plan",
      "display_order": 1,
      "button_text": "Choose Plan",
      "is_popular": false,
      "is_custom": false,
      "prices": {
        "monthly_inr": 0,
        "yearly_inr": 0,
        "monthly_usd": 0,
        "yearly_usd": 0,
        "yearly_monthly_inr": 0,
        "yearly_monthly_usd": 0
      },
      "limits": {
        "instagram_connections_limit": 3,
        "instagram_link_limit": 3,
        "actions_per_hour_limit": 100,
        "actions_per_day_limit": 100,
        "actions_per_month_limit": 1000
      },
      "enabledFeatures": [
        "unlimited_contacts",
        "post_comment_dm_reply",
        "post_comment_reply_automation",
        "reel_comment_dm_reply",
        "reel_comment_reply_automation",
        "share_reel_to_admin",
        "share_post_to_admin",
        "super_profile",
        "inbox_menu",
        "collect_email",
        "suggest_more",
        "followers_only",
        "once_per_user_24h",
        "comment_moderation",
        "seen_typing"
      ]
    },
    "basic": {
      "name": "Basic Plan",
      "display_order": 2,
      "button_text": "Choose Plan",
      "is_popular": false,
      "is_custom": false,
      "prices": {
        "monthly_inr": 599,
        "yearly_inr": 5988,
        "monthly_usd": 8,
        "yearly_usd": 72,
        "yearly_monthly_inr": 499,
        "yearly_monthly_usd": 6
      },
      "limits": {
        "instagram_connections_limit": 3,
        "instagram_link_limit": 3,
        "actions_per_hour_limit": 100,
        "actions_per_day_limit": 1000,
        "actions_per_month_limit": 25000
      },
      "enabledFeatures": [
        "unlimited_contacts",
        "post_comment_dm_reply",
        "post_comment_reply_automation",
        "reel_comment_dm_reply",
        "reel_comment_reply_automation",
        "share_reel_to_admin",
        "share_post_to_admin",
        "super_profile",
        "inbox_menu",
        "collect_email",
        "suggest_more",
        "followers_only",
        "once_per_user_24h",
        "comment_moderation",
        "seen_typing",
        "welcome_message",
        "convo_starters",
        "dm_automation",
        "story_automation",
        "no_watermark"
      ]
    },
    "pro": {
      "name": "Pro Plan",
      "display_order": 3,
      "button_text": "Choose Plan",
      "is_popular": true,
      "is_custom": false,
      "prices": {
        "monthly_inr": 999,
        "yearly_inr": 9588,
        "monthly_usd": 15,
        "yearly_usd": 144,
        "yearly_monthly_inr": 799,
        "yearly_monthly_usd": 12
      },
      "limits": {
        "instagram_connections_limit": 5,
        "instagram_link_limit": 5,
        "actions_per_hour_limit": 200,
        "actions_per_day_limit": 2500,
        "actions_per_month_limit": 70000
      },
      "enabledFeatures": [
        "unlimited_contacts",
        "post_comment_dm_reply",
        "post_comment_reply_automation",
        "reel_comment_dm_reply",
        "reel_comment_reply_automation",
        "share_reel_to_admin",
        "share_post_to_admin",
        "super_profile",
        "inbox_menu",
        "collect_email",
        "suggest_more",
        "followers_only",
        "once_per_user_24h",
        "comment_moderation",
        "seen_typing",
        "welcome_message",
        "convo_starters",
        "dm_automation",
        "story_automation",
        "no_watermark",
        "global_trigger",
        "mentions",
        "instagram_live_automation",
        "priority_support"
      ]
    },
    "ultra": {
      "name": "Ultra Plan",
      "display_order": 4,
      "button_text": "Choose Plan",
      "is_popular": false,
      "is_custom": false,
      "prices": {
        "monthly_inr": 1999,
        "yearly_inr": 19188,
        "monthly_usd": 25,
        "yearly_usd": 240,
        "yearly_monthly_inr": 1599,
        "yearly_monthly_usd": 20
      },
      "limits": {
        "instagram_connections_limit": 10,
        "instagram_link_limit": 10,
        "actions_per_hour_limit": 400,
        "actions_per_day_limit": 5000,
        "actions_per_month_limit": 100000
      },
      "enabledFeatures": [
        "unlimited_contacts",
        "post_comment_dm_reply",
        "post_comment_reply_automation",
        "reel_comment_dm_reply",
        "reel_comment_reply_automation",
        "share_reel_to_admin",
        "share_post_to_admin",
        "super_profile",
        "inbox_menu",
        "collect_email",
        "suggest_more",
        "followers_only",
        "once_per_user_24h",
        "comment_moderation",
        "seen_typing",
        "welcome_message",
        "convo_starters",
        "dm_automation",
        "story_automation",
        "no_watermark",
        "global_trigger",
        "mentions",
        "instagram_live_automation",
        "priority_support"
      ]
    }
  },
  "featureLayerMap": {
    "dm_automation": { "frontendSection": "DMAutomationView", "backendRoutes": ["/api/instagram/automations"], "workerBehavior": "DM keyword execution" },
    "global_trigger": { "frontendSection": "GlobalTriggersView", "backendRoutes": ["/api/instagram/automations"], "workerBehavior": "Global fallback" },
    "post_comment_dm_reply": { "frontendSection": "PostAutomationView", "backendRoutes": ["/api/instagram/automations"], "workerBehavior": "Post comment DM" },
    "post_comment_reply_automation": { "frontendSection": "PostAutomationView", "backendRoutes": ["/api/instagram/automations"], "workerBehavior": "Post comment reply" },
    "reel_comment_dm_reply": { "frontendSection": "ReelAutomationView", "backendRoutes": ["/api/instagram/automations"], "workerBehavior": "Reel comment DM" },
    "reel_comment_reply_automation": { "frontendSection": "ReelAutomationView", "backendRoutes": ["/api/instagram/automations"], "workerBehavior": "Reel comment reply" },
    "share_post_to_admin": { "frontendSection": "post editor", "backendRoutes": ["/api/instagram/automations"], "workerBehavior": "Post share trigger" },
    "share_reel_to_admin": { "frontendSection": "reel editor", "backendRoutes": ["/api/instagram/automations"], "workerBehavior": "Reel share trigger" },
    "welcome_message": { "frontendSection": "WelcomeMessageView", "backendRoutes": ["/api/instagram/automations"], "workerBehavior": "Welcome fallback" },
    "convo_starters": { "frontendSection": "ConvoStarterView", "backendRoutes": ["/api/instagram/convo-starters"], "workerBehavior": "Config automation" },
    "inbox_menu": { "frontendSection": "InboxMenu", "backendRoutes": ["/api/instagram/inbox-menu"], "workerBehavior": "Menu automation" },
    "story_automation": { "frontendSection": "StoryAutomationView", "backendRoutes": ["/api/instagram/automations"], "workerBehavior": "Story handling" },
    "mentions": { "frontendSection": "MentionsView", "backendRoutes": ["/api/instagram/mentions-config"], "workerBehavior": "Mention event handling" },
    "suggest_more": { "frontendSection": "SuggestMoreView", "backendRoutes": ["/api/instagram/suggest-more"], "workerBehavior": "Worker follow-up" },
    "comment_moderation": { "frontendSection": "CommentModerationView", "backendRoutes": ["/api/instagram/comment-moderation"], "workerBehavior": "Moderation action" },
    "collect_email": { "frontendSection": "EmailCollectorView", "backendRoutes": ["collector destination APIs"], "workerBehavior": "Pending email flow" },
    "instagram_live_automation": { "frontendSection": "LiveAutomationView", "backendRoutes": ["/api/instagram/automations"], "workerBehavior": "Live handling" },
    "followers_only": { "frontendSection": "automation toggle", "backendRoutes": ["/api/instagram/automations"], "workerBehavior": "Follower check" },
    "seen_typing": { "frontendSection": "automation toggle", "backendRoutes": ["/api/instagram/automations"], "workerBehavior": "Seen/typing prelude" },
    "once_per_user_24h": { "frontendSection": "automation toggle", "backendRoutes": ["/api/instagram/automations"], "workerBehavior": "Cooldown skip" },
    "super_profile": { "frontendSection": "SuperProfileView", "backendRoutes": ["/api/super-profile"], "workerBehavior": "Public profile availability" },
    "no_watermark": { "frontendSection": "template sending", "backendRoutes": ["plan context"], "workerBehavior": "Suppress watermark" },
    "priority_support": { "frontendSection": "plan/display only", "backendRoutes": [], "workerBehavior": "Display only" },
    "unlimited_contacts": { "frontendSection": "plan/display only", "backendRoutes": [], "workerBehavior": "Display only" }
  }
}
